electricalsim/Electrical_Grid_Simulator.py
electricalsim/__init__.py
electricalsim/config.ini
electricalsim/egs_create_shortcut.py
electricalsim/egs_run.py
electricalsim/version.py
electricalsim/NodeGraphQt6/__init__.py
electricalsim/NodeGraphQt6/constants.py
electricalsim/NodeGraphQt6/errors.py
electricalsim/NodeGraphQt6/pkg_info.py
electricalsim/NodeGraphQt6/base/__init__.py
electricalsim/NodeGraphQt6/base/commands.py
electricalsim/NodeGraphQt6/base/factory.py
electricalsim/NodeGraphQt6/base/graph.py
electricalsim/NodeGraphQt6/base/menu.py
electricalsim/NodeGraphQt6/base/model.py
electricalsim/NodeGraphQt6/base/node.py
electricalsim/NodeGraphQt6/base/port.py
electricalsim/NodeGraphQt6/custom_widgets/__init__.py
electricalsim/NodeGraphQt6/custom_widgets/nodes_palette.py
electricalsim/NodeGraphQt6/custom_widgets/nodes_tree.py
electricalsim/NodeGraphQt6/custom_widgets/properties_bin/__init__.py
electricalsim/NodeGraphQt6/custom_widgets/properties_bin/custom_widget_color_picker.py
electricalsim/NodeGraphQt6/custom_widgets/properties_bin/custom_widget_file_paths.py
electricalsim/NodeGraphQt6/custom_widgets/properties_bin/custom_widget_slider.py
electricalsim/NodeGraphQt6/custom_widgets/properties_bin/custom_widget_value_edit.py
electricalsim/NodeGraphQt6/custom_widgets/properties_bin/custom_widget_vectors.py
electricalsim/NodeGraphQt6/custom_widgets/properties_bin/node_property_factory.py
electricalsim/NodeGraphQt6/custom_widgets/properties_bin/node_property_widgets.py
electricalsim/NodeGraphQt6/custom_widgets/properties_bin/prop_widgets_abstract.py
electricalsim/NodeGraphQt6/custom_widgets/properties_bin/prop_widgets_base.py
electricalsim/NodeGraphQt6/nodes/__init__.py
electricalsim/NodeGraphQt6/nodes/backdrop_node.py
electricalsim/NodeGraphQt6/nodes/base_node.py
electricalsim/NodeGraphQt6/nodes/base_node_circle.py
electricalsim/NodeGraphQt6/nodes/group_node.py
electricalsim/NodeGraphQt6/nodes/port_node.py
electricalsim/NodeGraphQt6/qgraphics/__init__.py
electricalsim-0.0.8.21.dist-info/METADATA
electricalsim-0.0.8.21.dist-info/WHEEL
electricalsim-0.0.8.21.dist-info/entry_points.txt
electricalsim-0.0.8.21.dist-info/licenses/LICENSE
electricalsim-0.0.8.21.dist-info/RECORD
