Metadata-Version: 2.4
Name: electricalsim
Version: 0.0.8.21
Summary: Graphical user interface for simulating electrical networks based on the pandapower library
Project-URL: Homepage, https://github.com/aloytag/electrical-grid-simulator
Project-URL: Bug Tracker, https://github.com/aloytag/electrical-grid-simulator/issues
Project-URL: Repository, https://github.com/aloytag/electrical-grid-simulator
Author-email: "Dr. Ing. Ariel S. Loyarte" <aloyarte@frsf.utn.edu.ar>
License: MIT
License-File: LICENSE
Keywords: electrical networks,energy,pandapower,power systems,simulation
Classifier: License :: OSI Approved :: MIT License
Classifier: Operating System :: OS Independent
Classifier: Programming Language :: Python :: 3
Requires-Python: <3.12,>=3.10
Requires-Dist: fuzzysearch>=0.7.3
Requires-Dist: grid2op>=1.9.7
Requires-Dist: importlib-metadata>=4.11.3
Requires-Dist: lightsim2grid<0.10.0,>=0.7.1
Requires-Dist: matplotlib<3.10.0,>=3.6.0
Requires-Dist: numba<0.61.0,>=0.56.4
Requires-Dist: pandapower>=3.1.2
Requires-Dist: platformdirs>=3.0.0
Requires-Dist: pyarrow<19.0.0,>=15.0.0
Requires-Dist: pynput>=1.7.6
Requires-Dist: pyqt-toast-notification>=1.3.2
Requires-Dist: pyqtdarktheme>=2.1.0
Requires-Dist: pyshortcuts>=1.8.3
Requires-Dist: pyside6>=6.6.1
Requires-Dist: qtawesome>=1.3.1
Requires-Dist: qtpy>=2.4.1
Requires-Dist: requests>=2.30.0
Requires-Dist: xlsxwriter>=3.2.0
